stockpyl/__init__.py
stockpyl/demand_source.py
stockpyl/disruption_process.py
stockpyl/eoq.py
stockpyl/finite_horizon.py
stockpyl/gsm_helpers.py
stockpyl/gsm_serial.py
stockpyl/gsm_tree.py
stockpyl/helpers.py
stockpyl/instances.py
stockpyl/loss_functions.py
stockpyl/meio_general.py
stockpyl/newsvendor.py
stockpyl/node_state_vars.py
stockpyl/optimization.py
stockpyl/policy.py
stockpyl/rq.py
stockpyl/sim.py
stockpyl/sim_io.py
stockpyl/ss.py
stockpyl/ssm_serial.py
stockpyl/supply_chain_network.py
stockpyl/supply_chain_node.py
stockpyl/supply_chain_product.py
stockpyl/supply_uncertainty.py
stockpyl/wagner_whitin.py
stockpyl/datasets/stockpyl_instances.json
stockpyl-1.0.2.dist-info/LICENSE
stockpyl-1.0.2.dist-info/METADATA
stockpyl-1.0.2.dist-info/WHEEL
stockpyl-1.0.2.dist-info/top_level.txt
stockpyl-1.0.2.dist-info/RECORD
