Metadata-Version: 2.1
Name: stockpyl
Version: 1.0.2
Summary: A Python package for inventory optimization and simulation
Home-page: https://github.com/LarrySnyder/stockpyl
Author: Larry Snyder
Author-email: larry.snyder@lehigh.edu
License: MIT License
Keywords: inventory,optimization
Classifier: Development Status :: 5 - Production/Stable
Classifier: License :: OSI Approved :: MIT License
Classifier: Natural Language :: English
Classifier: Programming Language :: Python :: 3
Classifier: Topic :: Education
Classifier: Topic :: Office/Business
Classifier: Topic :: Scientific/Engineering
License-File: LICENSE
Requires-Dist: build>=0.0.2
Requires-Dist: jsonpickle>=1.0
Requires-Dist: matplotlib>=2.0
Requires-Dist: networkx>=2.0
Requires-Dist: numpy>=1.21
Requires-Dist: scipy>=1.6.0
Requires-Dist: setuptools>=70.0
Requires-Dist: sphinx==4.5.0
Requires-Dist: sphinx-rtd-theme>=1.0.0
Requires-Dist: sphinx-toolbox>=3.1.2
Requires-Dist: tabulate>=0.8.7
Requires-Dist: tqdm>=4.1.0
